aliyunsdkalidns/__init__.py
aliyunsdkalidns/endpoint.py
aliyunsdkalidns/request/__init__.py
aliyunsdkalidns/request/v20150109/AddCustomLineRequest.py
aliyunsdkalidns/request/v20150109/AddDnsCacheDomainRequest.py
aliyunsdkalidns/request/v20150109/AddDnsGtmAccessStrategyRequest.py
aliyunsdkalidns/request/v20150109/AddDnsGtmAddressPoolRequest.py
aliyunsdkalidns/request/v20150109/AddDnsGtmMonitorRequest.py
aliyunsdkalidns/request/v20150109/AddDomainBackupRequest.py
aliyunsdkalidns/request/v20150109/AddDomainGroupRequest.py
aliyunsdkalidns/request/v20150109/AddDomainRecordRequest.py
aliyunsdkalidns/request/v20150109/AddDomainRequest.py
aliyunsdkalidns/request/v20150109/AddGtmAccessStrategyRequest.py
aliyunsdkalidns/request/v20150109/AddGtmAddressPoolRequest.py
aliyunsdkalidns/request/v20150109/AddGtmMonitorRequest.py
aliyunsdkalidns/request/v20150109/AddGtmRecoveryPlanRequest.py
aliyunsdkalidns/request/v20150109/BindInstanceDomainsRequest.py
aliyunsdkalidns/request/v20150109/ChangeDomainGroupRequest.py
aliyunsdkalidns/request/v20150109/ChangeDomainOfDnsProductRequest.py
aliyunsdkalidns/request/v20150109/CopyGtmConfigRequest.py
aliyunsdkalidns/request/v20150109/CreatePdnsAppKeyRequest.py
aliyunsdkalidns/request/v20150109/CreatePdnsUdpIpSegmentRequest.py
aliyunsdkalidns/request/v20150109/DeleteCustomLinesRequest.py
aliyunsdkalidns/request/v20150109/DeleteDnsCacheDomainRequest.py
aliyunsdkalidns/request/v20150109/DeleteDnsGtmAccessStrategyRequest.py
aliyunsdkalidns/request/v20150109/DeleteDnsGtmAddressPoolRequest.py
aliyunsdkalidns/request/v20150109/DeleteDomainGroupRequest.py
aliyunsdkalidns/request/v20150109/DeleteDomainRecordRequest.py
aliyunsdkalidns/request/v20150109/DeleteDomainRequest.py
aliyunsdkalidns/request/v20150109/DeleteGtmAccessStrategyRequest.py
aliyunsdkalidns/request/v20150109/DeleteGtmAddressPoolRequest.py
aliyunsdkalidns/request/v20150109/DeleteGtmRecoveryPlanRequest.py
aliyunsdkalidns/request/v20150109/DeleteSubDomainRecordsRequest.py
aliyun_python_sdk_alidns-3.0.7.dist-info/LICENSE
aliyun_python_sdk_alidns-3.0.7.dist-info/METADATA
aliyun_python_sdk_alidns-3.0.7.dist-info/WHEEL
aliyun_python_sdk_alidns-3.0.7.dist-info/top_level.txt
aliyun_python_sdk_alidns-3.0.7.dist-info/RECORD
